{"hash":"f83d7accd156397415b5652caf76356c6c054154","data":{"talent":{"talent":"pastaroni-ravioli","talent_name":"Pastaroni Ravioli","description":"Hi y'all! My name is PastaroniRavioli and I'm your noodle demon, hog cranking, catfish-wheezing VTuber!","content":"<p>Hi y'all! My name is PastaroniRavioli and I'm your noodle demon, hog cranking, catfish-wheezing VTuber! I love playing multiplayer games to troll my friends, and I'm always here to make you laugh! ❤️</p>\n<p>You can find me on YouTube and Twitch, streaming 6 days a week!</p>\n","path":"/talent/pastaroni-ravioli/","img":"pasta"}},"context":{}}